kalabash_admin_relaydomains/__init__.py
kalabash_admin_relaydomains/app_settings.py
kalabash_admin_relaydomains/apps.py
kalabash_admin_relaydomains/factories.py
kalabash_admin_relaydomains/forms.py
kalabash_admin_relaydomains/general_callbacks.py
kalabash_admin_relaydomains/handlers.py
kalabash_admin_relaydomains/kalmonak_extension.py
kalabash_admin_relaydomains/lib.py
kalabash_admin_relaydomains/models.py
kalabash_admin_relaydomains/postfix_maps.py
kalabash_admin_relaydomains/tests.py
kalabash_admin_relaydomains/urls.py
kalabash_admin_relaydomains/views.py
kalabash_admin_relaydomains/locale/en/LC_MESSAGES/django.mo
kalabash_admin_relaydomains/locale/en/LC_MESSAGES/django.po
kalabash_admin_relaydomains/locale/en/LC_MESSAGES/djangojs.mo
kalabash_admin_relaydomains/locale/en/LC_MESSAGES/djangojs.po
kalabash_admin_relaydomains/locale/fr/LC_MESSAGES/django.mo
kalabash_admin_relaydomains/locale/fr/LC_MESSAGES/django.po
kalabash_admin_relaydomains/locale/fr/LC_MESSAGES/djangojs.mo
kalabash_admin_relaydomains/locale/fr/LC_MESSAGES/djangojs.po
kalabash_admin_relaydomains/migrations/0001_initial.py
kalabash_admin_relaydomains/migrations/0002_relaydomain_domain.py
kalabash_admin_relaydomains/migrations/0003_update_relaydomains.py
kalabash_admin_relaydomains/migrations/0004_auto_20150506_1609.py
kalabash_admin_relaydomains/migrations/__init__.py
kalabash_admin_relaydomains/static/kalabash_admin_relaydomains/js/relay_domains.js
kalabash_admin_relaydomains/templates/kalabash_admin_relaydomains/new_relaydomain_form.html
kalabash_admin_relaydomains/templates/kalabash_admin_relaydomains/relaydomain_form.html
kalabash_admin_relaydomains/templates/kalabash_admin_relaydomains/service_field.html
kalabash_admin_relaydomains-1.1.4.dist-info/LICENSE
kalabash_admin_relaydomains-1.1.4.dist-info/METADATA
kalabash_admin_relaydomains-1.1.4.dist-info/WHEEL
kalabash_admin_relaydomains-1.1.4.dist-info/top_level.txt
kalabash_admin_relaydomains-1.1.4.dist-info/RECORD
